CHANGELOG.txt
LICENSE.txt
MANIFEST.in
README.md
setup.py
pyrecruiter/__init__.py
pyrecruiter.egg-info/PKG-INFO
pyrecruiter.egg-info/SOURCES.txt
pyrecruiter.egg-info/dependency_links.txt
pyrecruiter.egg-info/requires.txt
pyrecruiter.egg-info/top_level.txt