Metadata-Version: 2.1
Name: pyrecruiter
Version: 0.0.9
Summary: This is a Light weight Open source Python Package made specially for Job Seekers and Recruiters in the field of Data science and Machine Learning (Currently), In order to use the Power of Machine Learning to help Shortlist the Right Candidates for a specific Job.
Home-page: https://github.com/msp04/PyRecruiter
Author: Mohit Singh Pawar
Author-email: mohitsinghpawar4@gmail.com
License: MIT
Keywords: job,recruit,recruiters,shortlister,pyrecruit,pyrecruiter,PyRecruiter
Platform: UNKNOWN
Classifier: Development Status :: 5 - Production/Stable
Classifier: Intended Audience :: Information Technology
Classifier: Operating System :: Microsoft :: Windows :: Windows 10
Classifier: License :: OSI Approved :: MIT License
Classifier: Programming Language :: Python :: 3
